odoo10_addon_project_stage_state-10.0.1.0.0.99.dev15-py3.8-nspkg.pth
odoo/addons/project_stage_state/README.rst
odoo/addons/project_stage_state/__init__.py
odoo/addons/project_stage_state/__manifest__.py
odoo/addons/project_stage_state/i18n/ar.po
odoo/addons/project_stage_state/i18n/bg.po
odoo/addons/project_stage_state/i18n/ca.po
odoo/addons/project_stage_state/i18n/de.po
odoo/addons/project_stage_state/i18n/el.po
odoo/addons/project_stage_state/i18n/el_GR.po
odoo/addons/project_stage_state/i18n/es.po
odoo/addons/project_stage_state/i18n/es_CR.po
odoo/addons/project_stage_state/i18n/es_MX.po
odoo/addons/project_stage_state/i18n/es_VE.po
odoo/addons/project_stage_state/i18n/fi.po
odoo/addons/project_stage_state/i18n/fr.po
odoo/addons/project_stage_state/i18n/gl.po
odoo/addons/project_stage_state/i18n/hr.po
odoo/addons/project_stage_state/i18n/hr_HR.po
odoo/addons/project_stage_state/i18n/hu.po
odoo/addons/project_stage_state/i18n/it.po
odoo/addons/project_stage_state/i18n/ja.po
odoo/addons/project_stage_state/i18n/lt.po
odoo/addons/project_stage_state/i18n/lv.po
odoo/addons/project_stage_state/i18n/mk.po
odoo/addons/project_stage_state/i18n/mn.po
odoo/addons/project_stage_state/i18n/nb.po
odoo/addons/project_stage_state/i18n/nb_NO.po
odoo/addons/project_stage_state/i18n/nl.po
odoo/addons/project_stage_state/i18n/nl_NL.po
odoo/addons/project_stage_state/i18n/pl.po
odoo/addons/project_stage_state/i18n/project_stage_state.pot
odoo/addons/project_stage_state/i18n/pt.po
odoo/addons/project_stage_state/i18n/pt_BR.po
odoo/addons/project_stage_state/i18n/pt_PT.po
odoo/addons/project_stage_state/i18n/ro.po
odoo/addons/project_stage_state/i18n/ru.po
odoo/addons/project_stage_state/i18n/sk.po
odoo/addons/project_stage_state/i18n/sl.po
odoo/addons/project_stage_state/i18n/sv.po
odoo/addons/project_stage_state/i18n/tr.po
odoo/addons/project_stage_state/i18n/uk.po
odoo/addons/project_stage_state/i18n/zh_CN.po
odoo/addons/project_stage_state/models/__init__.py
odoo10_addon_project_stage_state-10.0.1.0.0.99.dev15.dist-info/METADATA
odoo10_addon_project_stage_state-10.0.1.0.0.99.dev15.dist-info/WHEEL
odoo10_addon_project_stage_state-10.0.1.0.0.99.dev15.dist-info/namespace_packages.txt
odoo10_addon_project_stage_state-10.0.1.0.0.99.dev15.dist-info/top_level.txt
odoo10_addon_project_stage_state-10.0.1.0.0.99.dev15.dist-info/RECORD
