Metadata-Version: 2.1
Name: odoo10-addon-project-stage-state
Version: 10.0.1.0.0.99.dev15
Summary: Restore State attribute removed from Project Stages in 8.0
Home-page: https://github.com/OCA/project-service
Author: Daniel Reis,Odoo Community Association (OCA)
Author-email: support@odoo-community.org
License: AGPL-3
Platform: UNKNOWN
Classifier: Programming Language :: Python
Classifier: Framework :: Odoo
Classifier: Framework :: Odoo :: 10.0
Classifier: License :: OSI Approved :: GNU Affero General Public License v3
Requires-Python: ~=2.7
Requires-Dist: odoo (<10.1dev,>=10.0)
